[
    {
        "id": "b26f23f8c9d1a25c",
        "type": "tab",
        "label": "Chuva Dashboard",
        "disabled": false,
        "info": ""
    },
    {
        "id": "9ec2dc44b2c8ecbb",
        "type": "mqtt in",
        "z": "b26f23f8c9d1a25c",
        "name": "Intensidade da Chuva",
        "topic": "esp32/sensorChuva/analog",
        "qos": "0",
        "datatype": "auto",
        "broker": "d5ad1b382c0dcf63",
        "nl": false,
        "rap": false,
        "rh": 0,
        "inputs": 0,
        "x": 640,
        "y": 100,
        "wires": [
            [
                "e1cca494748c3861"
            ]
        ]
    },
    {
        "id": "e1cca494748c3861",
        "type": "ui_chart",
        "z": "b26f23f8c9d1a25c",
        "name": "Gráfico Intensidade",
        "group": "c28fcad1f46dce84",
        "order": 1,
        "width": 0,
        "height": 0,
        "label": "Intensidade da Chuva",
        "chartType": "line",
        "legend": "false",
        "xformat": "HH:mm:ss",
        "interpolate": "linear",
        "nodata": "",
        "dot": false,
        "ymin": "0",
        "ymax": "4095",
        "removeOlder": 1,
        "removeOlderPoints": "",
        "removeOlderUnit": "3600",
        "cutout": 0,
        "useOneColor": false,
        "colors": [
            "#1f77b4",
            "#aec7e8",
            "#ff7f0e"
        ],
        "outputs": 1,
        "x": 910,
        "y": 100,
        "wires": [
            []
        ]
    },
    {
        "id": "7c1f34023c8c28b8",
        "type": "ui_gauge",
        "z": "b26f23f8c9d1a25c",
        "name": "Intensidade da Chuva",
        "group": "c28fcad1f46dce84",
        "order": 3,
        "width": 0,
        "height": 0,
        "gtype": "gage",
        "title": "Intensidade da Chuva",
        "label": "Chuva",
        "format": "{{msg.payload}}",
        "min": "0",
        "max": "4095",
        "colors": [
            "#00FF00",
            "#FFFF00",
            "#FFA500",
            "#FF0000"
        ],
        "x": 910,
        "y": 260,
        "wires": []
    },
    {
        "id": "20af487d5f711a61",
        "type": "mqtt in",
        "z": "b26f23f8c9d1a25c",
        "name": "Estado CHUVA/SECO",
        "topic": "esp32/sensorChuva",
        "qos": "0",
        "datatype": "auto",
        "broker": "d5ad1b382c0dcf63",
        "nl": false,
        "rap": false,
        "rh": 0,
        "inputs": 0,
        "x": 640,
        "y": 180,
        "wires": [
            [
                "fcf008c9c08b282f"
            ]
        ]
    },
    {
        "id": "fcf008c9c08b282f",
        "type": "ui_text",
        "z": "b26f23f8c9d1a25c",
        "group": "c28fcad1f46dce84",
        "order": 2,
        "width": 0,
        "height": 0,
        "name": "Estado Texto",
        "label": "Estado do Sensor:",
        "format": "{{msg.payload}}",
        "layout": "row-spread",
        "className": "{{msg.className}}",
        "x": 910,
        "y": 180,
        "wires": []
    },
    {
        "id": "933d44462d16042e",
        "type": "ui_switch",
        "z": "b26f23f8c9d1a25c",
        "name": "Controle LED",
        "label": "LED",
        "group": "c28fcad1f46dce84",
        "order": 4,
        "width": "4",
        "height": "1",
        "passthru": true,
        "topic": "esp32/controle",
        "x": 910,
        "y": 340,
        "wires": [
            []
        ]
    },
    {
        "id": "d5ad1b382c0dcf63",
        "type": "mqtt-broker",
        "name": "HiveMQ Broker",
        "broker": "broker.hivemq.com",
        "port": "1883",
        "clientid": "",
        "autoConnect": true,
        "usetls": false,
        "protocolVersion": "4",
        "keepalive": "60",
        "cleansession": true,
        "birthTopic": "",
        "birthQos": "0",
        "birthPayload": "",
        "closeTopic": "",
        "closePayload": "",
        "willTopic": "",
        "willQos": "0",
        "willPayload": ""
    },
    {
        "id": "c28fcad1f46dce84",
        "type": "ui_group",
        "name": "Chuva",
        "tab": "9c5ad82663349662",
        "order": 1,
        "disp": true,
        "width": "6",
        "collapse": false,
        "className": ""
    },
    {
        "id": "9c5ad82663349662",
        "type": "ui_tab",
        "name": "Dashboard",
        "icon": "dashboard",
        "disabled": false,
        "hidden": false
    },
    {
        "id": "9489c2566838c00a",
        "type": "global-config",
        "env": [],
        "modules": {
            "node-red-dashboard": "3.6.6"
        }
    }
]